LICENSE
MANIFEST.in
README.rst
manage.py
requirements.txt
scrapy.cfg
setup.py
nboot/__init__.py
nboot/settings.py
nboot/urls.py
nboot/version.py
nboot/wsgi.py
nbot/__init__.py
nbot/admin.py
nbot/apps.py
nbot/items.py
nbot/models.py
nbot/pipelines.py
nbot/settings.py
nbot/tests.py
nbot/views.py
nbot/migrations/__init__.py
nbot/spiders/__init__.py
nbot/spiders/toscrape-css.py
nbot/spiders/toscrape-xpath.py
nmdm/__init__.py
nmdm/admin.py
nmdm/apps.py
nmdm/initscript.py
nmdm/models.py
nmdm/tests.py
nmdm/urls.py
nmdm/version.py
nmdm/views.py
nmdm/migrations/0001_initial.py
nmdm/migrations/__init__.py
nmdm/templates/nmdm/index.html
nomono.egg-info/PKG-INFO
nomono.egg-info/SOURCES.txt
nomono.egg-info/dependency_links.txt
nomono.egg-info/requires.txt
nomono.egg-info/top_level.txt
npolling/__init__.py
npolling/admin.py
npolling/apps.py
npolling/flows.py
npolling/models.py
npolling/tests.py
npolling/urls.py
npolling/views.py
npolling/migrations/0001_initial.py
npolling/migrations/0002_auto_20170712_0134.py
npolling/migrations/__init__.py
npolling/templates/npolling/index.html